mkpiano/__init__.py
mkpiano/boards/__init__.py
mkpiano/boards/base/__init__.py
mkpiano/boards/mbuild/__init__.py
mkpiano/comm/SerialPort/__init__.py
mkpiano/driver/CH341PT.DLL
mkpiano/driver/CH341S64.SYS
mkpiano/driver/CH341S98.SYS
mkpiano/driver/CH341SER.CAT
mkpiano/driver/CH341SER.INF
mkpiano/driver/CH341SER.SYS
mkpiano/driver/CH341SER.VXD
mkpiano/driver/ch34x_install.exe
mkpiano/driver/ch34x_install.pkg
mkpiano/driver/DRVSETUP64/DRVSETUP64.exe
mkpiano/modules/mbuild/__init__.py
mkpiano/modules/mbuild/modules.py
mkpiano/protocols/PackData.py
mkpiano/protocols/Protocols.py
mkpiano/protocols/__init__.py
mkpiano/utils/__init__.py
xespiano-0.0.5.dist-info/METADATA
xespiano-0.0.5.dist-info/WHEEL
xespiano-0.0.5.dist-info/top_level.txt
xespiano-0.0.5.dist-info/RECORD
