Metadata-Version: 2.1
Name: xespiano
Version: 0.0.5
Summary: library for makeblock fingertip piano
Home-page: https://makeblock.com
Author: makeblock
Author-email: flashindream@gmail.com
License: UNKNOWN
Platform: UNKNOWN
Requires-Dist: pyserial
